{
  "db_name": "PostgreSQL",
  "query": "\n            INSERT INTO \"Document\" (id, owner, name, \"fileType\", \"projectId\", \"createdAt\", \"updatedAt\")\n            VALUES ($1, $2, $3, $4, $5, $6, $6)\n        ",
  "describe": {
    "columns": [],
    "parameters": {
      "Left": [
        "Text",
        "Text",
        "Text",
        "Text",
        "Text",
        "Timestamp"
      ]
    },
    "nullable": []
  },
  "hash": "7c4cd009982b182b18927dc5671aad059a55440c2de73c818ef28d6cf08acf80"
}
