{
  "db_name": "PostgreSQL",
  "query": "\n            SELECT *\n            FROM\n                frecency_events\n            WHERE was_processed = false\n            LIMIT $1\n            ",
  "describe": {
    "columns": [
      {
        "ordinal": 0,
        "name": "id",
        "type_info": "Int8"
      },
      {
        "ordinal": 1,
        "name": "user_id",
        "type_info": "Text"
      },
      {
        "ordinal": 2,
        "name": "entity_type",
        "type_info": "Text"
      },
      {
        "ordinal": 3,
        "name": "event_type",
        "type_info": "Text"
      },
      {
        "ordinal": 4,
        "name": "timestamp",
        "type_info": "Timestamptz"
      },
      {
        "ordinal": 5,
        "name": "connection_id",
        "type_info": "Text"
      },
      {
        "ordinal": 6,
        "name": "entity_id",
        "type_info": "Text"
      },
      {
        "ordinal": 7,
        "name": "was_processed",
        "type_info": "Bool"
      }
    ],
    "parameters": {
      "Left": [
        "Int8"
      ]
    },
    "nullable": [
      false,
      false,
      false,
      false,
      false,
      false,
      false,
      false
    ]
  },
  "hash": "d42e3270642ca0b9eff6b5807f600c24fd26d50d612a66edf0738c62d15680ba"
}
